kimwonjoon_cmd/__init__.py
kimwonjoon_cmd/cmd.py
kimwonjoon_cmd-0.1.1.dist-info/METADATA
kimwonjoon_cmd-0.1.1.dist-info/WHEEL
kimwonjoon_cmd-0.1.1.dist-info/entry_points.txt
kimwonjoon_cmd-0.1.1.dist-info/top_level.txt
kimwonjoon_cmd-0.1.1.dist-info/RECORD
